{
  "id": "m_0089_01",
  "createdDateTime": null,
  "lastModifiedDateTime": null,
  "changeKey": null,
  "categories": [],
  "receivedDateTime": "2025-08-06T05:54:20.211000+00:00",
  "sentDateTime": "2025-08-06T05:53:55.157000+00:00",
  "hasAttachments": false,
  "internetMessageId": "<2505599623.833629@testdomain.com>",
  "internetMessageHeaders": [
    {
      "name": "From",
      "value": "Harper Hill <harper.hill+36@testdomain.com>"
    },
    {
      "name": "To",
      "value": "Alex Taylor <alex@wavetogether.com>"
    },
    {
      "name": "Subject",
      "value": "Heads up on release timing"
    },
    {
      "name": "Date",
      "value": "2025-08-06T05:53:55.157000+00:00"
    },
    {
      "name": "Message-ID",
      "value": "<2505599623.833629@testdomain.com>"
    }
  ],
  "subject": "Heads up on release timing",
  "bodyPreview": "Hi, Following up with a few details from our chat. We aligned on the core requirements and trimmed a few nice\u2011to\u2011have items so we can hit the target date. I included concrete examples for the payloads so we avoid ambiguity later. - Scope: finalize API con",
  "body": {
    "contentType": "HTML",
    "content": "<html><body><p>Hi,</p>\n<p>Following up with a few details from our chat.</p>\n<p>We aligned on the core requirements and trimmed a few nice\u2011to\u2011have items so we can hit the target date. I included concrete examples for the payloads so we avoid ambiguity later.</p>\n<ul><li>Scope: finalize API contract (auth, pagination, errors)</li><li>Risks: rate limiting during onboarding, CSV import memory spikes</li><li>Timeline: cut beta by next Wednesday, GA in two weeks</li><li>Owners: backend \u2014 me; frontend \u2014 pairing with design</li></ul>\n<p>If anything looks off, let me know and I\u2019ll adjust.</p></body></html>"
  },
  "importance": "normal",
  "parentFolderId": "inbox",
  "conversationId": "cv_0089",
  "conversationIndex": null,
  "isDeliveryReceiptRequested": false,
  "isReadReceiptRequested": false,
  "isRead": false,
  "isDraft": false,
  "from": {
    "emailAddress": {
      "name": "Harper Hill",
      "address": "harper.hill+36@testdomain.com"
    }
  },
  "sender": {
    "emailAddress": {
      "name": "Harper Hill",
      "address": "harper.hill+36@testdomain.com"
    }
  },
  "toRecipients": [
    {
      "emailAddress": {
        "name": "Alex Taylor",
        "address": "alex@wavetogether.com"
      }
    }
  ],
  "ccRecipients": [],
  "bccRecipients": [],
  "replyTo": [],
  "webLink": null
}