{
  "id": "m_0182_01",
  "createdDateTime": null,
  "lastModifiedDateTime": null,
  "changeKey": null,
  "categories": [],
  "receivedDateTime": "2025-07-28T18:23:27.767000+00:00",
  "sentDateTime": "2025-07-28T18:23:00.362000+00:00",
  "hasAttachments": false,
  "internetMessageId": "<3726617340.184036@testdomain.com>",
  "internetMessageHeaders": [
    {
      "name": "From",
      "value": "Zoey Miller <zoey.miller+45@testdomain.com>"
    },
    {
      "name": "To",
      "value": "Alex Taylor <alex@wavetogether.com>"
    },
    {
      "name": "Subject",
      "value": "RE: Invoice overpayment detected"
    },
    {
      "name": "Date",
      "value": "2025-07-28T18:23:00.362000+00:00"
    },
    {
      "name": "Message-ID",
      "value": "<3726617340.184036@testdomain.com>"
    }
  ],
  "subject": "RE: Invoice overpayment detected",
  "bodyPreview": "Good morning, Thanks for the quick turnaround on this. For testing, I\u2019ll start with a small cohort and track error rates, latency, and activation. If metrics look stable we can roll out to a larger slice by end of day. For testing, I\u2019ll start with a small",
  "body": {
    "contentType": "HTML",
    "content": "<html><body><p>Good morning,</p>\n<p>Thanks for the quick turnaround on this.</p>\n<p>For testing, I\u2019ll start with a small cohort and track error rates, latency, and activation. If metrics look stable we can roll out to a larger slice by end of day.</p>\n<p>For testing, I\u2019ll start with a small cohort and track error rates, latency, and activation. If metrics look stable we can roll out to a larger slice by end of day.</p>\n<ul><li>Scope: finalize API contract (auth, pagination, errors)</li><li>Risks: rate limiting during onboarding, CSV import memory spikes</li><li>Timeline: cut beta by next Wednesday, GA in two weeks</li><li>Owners: backend \u2014 me; frontend \u2014 pairing with design</li></ul>\n<p>Happy to jump on a quick call later today.</p></body></html>"
  },
  "importance": "normal",
  "parentFolderId": "junkemail",
  "conversationId": "cv_0182",
  "conversationIndex": null,
  "isDeliveryReceiptRequested": false,
  "isReadReceiptRequested": false,
  "isRead": true,
  "isDraft": false,
  "from": {
    "emailAddress": {
      "name": "Zoey Miller",
      "address": "zoey.miller+45@testdomain.com"
    }
  },
  "sender": {
    "emailAddress": {
      "name": "Zoey Miller",
      "address": "zoey.miller+45@testdomain.com"
    }
  },
  "toRecipients": [
    {
      "emailAddress": {
        "name": "Alex Taylor",
        "address": "alex@wavetogether.com"
      }
    }
  ],
  "ccRecipients": [],
  "bccRecipients": [],
  "replyTo": [],
  "webLink": null
}